exp1572
