Metadata-Version: 2.1
Name: exp1572
Version: 1.0.1.10.4
Summary: Game "1572: The Lost Expedition"
Home-page: https://github.com/witdba/exp1572
Author: Vitaliy Serdakovskiy
Author-email: witdba@gmail.com
License: UNKNOWN
Project-URL: Bug Reports, https://github.com/witdba/ exp1572/issues
Project-URL: Say Thanks!, http://saythanks.io/to/witdba
Project-URL: Source, https://github.com/witdba/exp1572
Keywords: python console game manager
Platform: UNKNOWN
Classifier: Development Status :: 4 - Beta
Classifier: Intended Audience :: End Users/Desktop
Classifier: Topic :: Games/Entertainment
Classifier: Topic :: Games/Entertainment :: Board Games
Classifier: License :: OSI Approved :: GNU General Public License v2 (GPLv2)
Classifier: Programming Language :: Python :: 3
Classifier: Programming Language :: Python :: 3.4
Classifier: Programming Language :: Python :: 3.5
Classifier: Programming Language :: Python :: 3.6
Classifier: Programming Language :: Python :: 3.7
Requires-Python: >=3.0.*
